lattice/__init__.py
lattice/elastic/__init__.py
lattice/elastic/agent/__init__.py
lattice/elastic/agent/server/__init__.py
lattice/elastic/agent/server/api.py
lattice/elastic/agent/server/get_notices.py
lattice/elastic/agent/server/lattice_agent.py
lattice/elastic/events/__init__.py
lattice/elastic/events/api.py
lattice/elastic/events/handlers.py
lattice/elastic/multiprocessing/__init__.py
lattice/elastic/multiprocessing/api.py
lattice/elastic/multiprocessing/redirects.py
lattice/elastic/multiprocessing/tail_log.py
lattice/elastic/multiprocessing/errors/__init__.py
lattice/elastic/multiprocessing/errors/error_handler.py
lattice/elastic/multiprocessing/errors/handlers.py
lattice/elastic/rendezvous/__init__.py
lattice/elastic/rendezvous/api.py
lattice/elastic/rendezvous/dynamic_rendezvous.py
lattice/elastic/rendezvous/etcd_rendezvous.py
lattice/elastic/rendezvous/etcd_rendezvous_backend.py
lattice/elastic/rendezvous/etcd_server.py
lattice/elastic/rendezvous/etcd_store.py
lattice/elastic/rendezvous/registry.py
lattice/elastic/rendezvous/utils.py
lattice/elastic/utils/__init__.py
lattice/elastic/utils/api.py
lattice/elastic/utils/log_level.py
lattice/elastic/utils/logging.py
lattice/elastic/utils/store.py
lattice/torch/__init__.py
lattice/torch/run.py
lattice/torch/launcher/__init__.py
lattice/torch/launcher/api.py
lattice_agent-0.1.2.dist-info/METADATA
lattice_agent-0.1.2.dist-info/WHEEL
lattice_agent-0.1.2.dist-info/top_level.txt
lattice_agent-0.1.2.dist-info/RECORD
