Metadata-Version: 2.1
Name: lattice-agent
Version: 0.1.2
Summary: Lattice Agent
Requires-Python: >=3.7
Requires-Dist: GPUtil
Requires-Dist: python-etcd
Requires-Dist: requests
